plone/meta/__init__.py
plone/meta/config_package.py
plone/meta/multi_call.py
plone/meta/pep_420.py
plone/meta/re_enable_actions.py
plone/meta/default/changelog_template.jinja
plone/meta/default/dependabot.yml
plone/meta/default/editorconfig.j2
plone/meta/default/flake8.j2
plone/meta/default/gitignore.j2
plone/meta/default/gitlab-ci.yml.j2
plone/meta/default/meta.yml.j2
plone/meta/default/packages.txt
plone/meta/default/pre-commit-config.yaml.j2
plone/meta/default/pyproject.toml.j2
plone/meta/default/test-matrix.yml.j2
plone/meta/default/tox-base.j2
plone/meta/default/tox-init.j2
plone/meta/default/tox-plone-depending-qa.j2
plone/meta/default/tox-qa.j2
plone/meta/default/tox-test-coverage.j2
plone/meta/default/tox-test-runner-specifics.j2
plone/meta/default/tox.ini.j2
plone/meta/shared/__init__.py
plone/meta/shared/call.py
plone/meta/shared/git.py
plone/meta/shared/packages.py
plone/meta/shared/path.py
plone/meta/shared/utils.py
plone_meta-2.3.1.dist-info/licenses/LICENSE
plone_meta-2.3.1.dist-info/METADATA
plone_meta-2.3.1.dist-info/WHEEL
plone_meta-2.3.1.dist-info/entry_points.txt
plone_meta-2.3.1.dist-info/top_level.txt
plone_meta-2.3.1.dist-info/RECORD
