Metadata-Version: 2.4
Name: plone.meta
Version: 2.3.1
Summary: Applies a standard set of configuration files for Plone repositories
Author-email: Plone Foundation <releaseteam@plone.org>, Gil Forcada Codinachs <gil.gnome@gmail.com>
License:                     GNU GENERAL PUBLIC LICENSE
Project-URL: Homepage, https://github.com/plone/meta
Project-URL: Issue Tracker, https://github.com/plone/meta/issues
Project-URL: Changelog, https://github.com/plone/meta/blob/2.x/CHANGES.md
Project-URL: Documentation, https://6.docs.plone.org/developer-guide/standardize-python-project-configuration.html
Keywords: plone,packaging
Classifier: Development Status :: 4 - Beta
Classifier: Intended Audience :: Developers
Classifier: License :: OSI Approved :: GNU General Public License v2 (GPLv2)
Classifier: Programming Language :: Python
Classifier: Programming Language :: Python :: 3
Classifier: Programming Language :: Python :: 3.10
Classifier: Programming Language :: Python :: 3.11
Classifier: Programming Language :: Python :: 3.12
Classifier: Programming Language :: Python :: 3.13
Classifier: Programming Language :: Python :: Implementation :: CPython
Classifier: Natural Language :: English
Classifier: Operating System :: OS Independent
Requires-Python: >=3.10
License-File: LICENSE
Requires-Dist: Jinja2
Requires-Dist: editorconfig
Requires-Dist: pyyaml
Requires-Dist: tomlkit
Requires-Dist: tox
Requires-Dist: validate-pyproject[all]
Requires-Dist: zest.releaser
Dynamic: license-file
